CHANGELOG.md
LICENSE
MANIFEST.in
README.md
setup.py
cpu/include/ball_query.h
cpu/include/cloud.h
cpu/include/compat.h
cpu/include/fps.h
cpu/include/interpolate.h
cpu/include/knn.h
cpu/include/nanoflann.hpp
cpu/include/neighbors.h
cpu/include/utils.h
cpu/src/ball_query.cpp
cpu/src/bindings.cpp
cpu/src/fps.cpp
cpu/src/interpolate.cpp
cpu/src/knn.cpp
cpu/src/neighbors.cpp
cuda/include/ball_query.h
cuda/include/chamfer_dist.h
cuda/include/compat.h
cuda/include/cubic_feature_sampling.h
cuda/include/cuda_utils.h
cuda/include/gridding.h
cuda/include/interpolate.h
cuda/include/metrics.h
cuda/include/sampling.h
cuda/include/utils.h
cuda/src/ball_query.cpp
cuda/src/ball_query_gpu.cu
cuda/src/bindings.cpp
cuda/src/chamfer_dist.cpp
cuda/src/chamfer_dist_gpu.cu
cuda/src/cubic_feature_sampling.cpp
cuda/src/cubic_feature_sampling_gpu.cu
cuda/src/gridding.cpp
cuda/src/gridding_gpu.cu
cuda/src/interpolate.cpp
cuda/src/interpolate_gpu.cu
cuda/src/metrics.cpp
cuda/src/metrics_gpu.cu
cuda/src/sampling.cpp
cuda/src/sampling_gpu.cu
torch_points_kernels/__init__.py
torch_points_kernels/chamfer_dist.py
torch_points_kernels/cluster.py
torch_points_kernels/cubic_feature_sampling.py
torch_points_kernels/gridding.py
torch_points_kernels/knn.py
torch_points_kernels/metrics.py
torch_points_kernels/torchpoints.py
torch_points_kernels.egg-info/PKG-INFO
torch_points_kernels.egg-info/SOURCES.txt
torch_points_kernels.egg-info/dependency_links.txt
torch_points_kernels.egg-info/requires.txt
torch_points_kernels.egg-info/top_level.txt