Metadata-Version: 2.1
Name: torch-points-kernels
Version: 0.7.0
Summary: PyTorch kernels for spatial operations on point clouds
Home-page: https://github.com/nicolas-chaulet/torch-points-kernels
Author: Nicolas Chaulet
License: UNKNOWN
Download-URL: https://github.com/nicolas-chaulet/torch-points-kernels/archive/0.7.0.tar.gz
Platform: UNKNOWN
Classifier: Programming Language :: Python :: 3
Classifier: License :: OSI Approved :: MIT License
